drf_methods/__init__.py
drf_methods-0.3.dist-info/LICENCE.txt
drf_methods-0.3.dist-info/METADATA
drf_methods-0.3.dist-info/WHEEL
drf_methods-0.3.dist-info/top_level.txt
drf_methods-0.3.dist-info/RECORD
